itemloaders/__init__.py
itemloaders/common.py
itemloaders/processors.py
itemloaders/py.typed
itemloaders/utils.py
itemloaders-1.3.1.dist-info/LICENSE
itemloaders-1.3.1.dist-info/METADATA
itemloaders-1.3.1.dist-info/WHEEL
itemloaders-1.3.1.dist-info/top_level.txt
itemloaders-1.3.1.dist-info/RECORD
