Metadata-Version: 2.1
Name: itemloaders
Version: 1.3.1
Summary: Base library for scrapy's ItemLoader
Home-page: https://github.com/scrapy/itemloaders
Author: Zyte
Author-email: opensource@zyte.com
License: BSD
Project-URL: Documentation, https://itemloaders.readthedocs.io/
Project-URL: Source, https://github.com/scrapy/itemloaders
Classifier: Development Status :: 5 - Production/Stable
Classifier: Intended Audience :: Developers
Classifier: License :: OSI Approved :: BSD License
Classifier: Operating System :: OS Independent
Classifier: Programming Language :: Python
Classifier: Programming Language :: Python :: 3
Classifier: Programming Language :: Python :: 3.8
Classifier: Programming Language :: Python :: 3.9
Classifier: Programming Language :: Python :: 3.10
Classifier: Programming Language :: Python :: 3.11
Classifier: Programming Language :: Python :: 3.12
Classifier: Programming Language :: Python :: Implementation :: CPython
Classifier: Programming Language :: Python :: Implementation :: PyPy
Requires-Python: >=3.8
License-File: LICENSE
Requires-Dist: w3lib>=1.17.0
Requires-Dist: parsel>=1.5.0
Requires-Dist: jmespath>=0.9.5
Requires-Dist: itemadapter>=0.1.0
